{"items":[{"id":"mrdpe2sonxvph","type":"sito","title":"Alcolici Jap","url":"https://www.saketora.com/","category":"Alcol","note":"Verificare che spediscano in Italia\nBuyee ogni tanto ha coupon!","price":"","priority":"","vpn":false,"image":null,"links":[],"pinned":false,"createdAt":1783613440680,"updatedAt":1783613440680,"views":0},{"id":"mrdpforjxe3ka","type":"sito","title":"Carte Jap","url":"https://www.ka-nabell.com/ec/sell/pokemon","category":"Carte","note":"Buyee ogni tanto ha coupon!\nSembra meno conveniente di HARERUYA2","price":"","priority":"","vpn":false,"image":null,"links":[],"pinned":false,"createdAt":1783613515807,"updatedAt":1783613515807,"views":0},{"id":"mrdphirus6gdu","type":"sito","title":"Carte Jap","url":"https://www.hareruya2.com/","category":"Carte","note":"Verificare che si possa comprare tramite Buyee","price":"","priority":"","vpn":false,"image":null,"links":[],"pinned":false,"createdAt":1783613601354,"updatedAt":1783613601354,"views":0},{"id":"mrdpjzrv9acqj","type":"sito","title":"Etsy Jap","url":"https://www.creema.jp/","category":"Handmade","note":"","price":"","priority":"","vpn":false,"image":null,"links":[],"pinned":false,"createdAt":1783613716699,"updatedAt":1783613716699,"views":0}],"deleted":{"mrdpmf6zx6x1j":1783614421840},"savedAt":1783614424051}